sentry_plugin_dingtalk/__init__.py
sentry_plugin_dingtalk/forms.py
sentry_plugin_dingtalk/plugin.py
sentry_plugin_dingtalk/template.py
sentry_plugin_dingtalk-0.1.2.dist-info/LICENSE
sentry_plugin_dingtalk-0.1.2.dist-info/METADATA
sentry_plugin_dingtalk-0.1.2.dist-info/WHEEL
sentry_plugin_dingtalk-0.1.2.dist-info/entry_points.txt
sentry_plugin_dingtalk-0.1.2.dist-info/top_level.txt
sentry_plugin_dingtalk-0.1.2.dist-info/RECORD
