Metadata-Version: 2.1
Name: sentry-plugin-dingtalk
Version: 0.1.2
Summary: A Sentry extension which send errors stats to dingtalk
Author: ding
Author-email: ding@ding.com
License: MIT
Keywords: sentry dingtalk
Classifier: Programming Language :: Python :: 3
Classifier: License :: OSI Approved :: MIT License
License-File: LICENSE
Requires-Dist: sentry >=9.0.0
Requires-Dist: requests
